apoc_data-0.1.2.dist-info/METADATA
apoc_data-0.1.2.dist-info/WHEEL
apoc_data/__init__.py
apoc_data/download.py
apoc_data/scrape/__init__.py
apoc_data/scrape/__main__.py
apoc_data/scrape/_filters.py
apoc_data/scrape/_scraper.py
apoc_data-0.1.2.dist-info/RECORD
