Metadata-Version: 2.1
Name: apoc-data
Version: 0.1.2
Summary: Data from the Alaska Public Offices Commission.
Author-Email: Nick Crews <nicholas.b.crews@gmail.com>
License: MIT
Requires-Python: >=3.9
